finflux/__init__.py
finflux/base_var.py
finflux/bond.py
finflux/equity.py
finflux/indicator.py
finflux/top.py
finflux-0.4.0.dist-info/METADATA
finflux-0.4.0.dist-info/WHEEL
finflux-0.4.0.dist-info/top_level.txt
finflux-0.4.0.dist-info/RECORD
