Metadata-Version: 2.4
Name: finflux
Version: 0.4.0
Summary: A Python wrapper for fetching financial and economic data
Author-email: Ingyu Bahng <ibahng21@gmail.com>
License-Expression: MIT
Project-URL: Documentation, https://finflux.readthedocs.io/en/latest/index.html
Project-URL: Repository, https://github.com/ibahng/finflux/tree/main
Keywords: finance,api,stocks,indicators,bonds
Requires-Python: >=3.13
Requires-Dist: requests<3.0,>=2.32.4
Requires-Dist: pandas<3.0,>=2.3.1
Requires-Dist: numpy<3.0,>=2.3.1
Requires-Dist: yfinance<1.0,>=0.2.65
Requires-Dist: matplotlib<4.0,>=3.10.3
